a5orchestrator/OrchestratorAPI.py
a5orchestrator/__init__.py
a5orchestrator-1.0.7.dist-info/LICENSE.txt
a5orchestrator-1.0.7.dist-info/METADATA
a5orchestrator-1.0.7.dist-info/WHEEL
a5orchestrator-1.0.7.dist-info/top_level.txt
a5orchestrator-1.0.7.dist-info/RECORD
