Metadata-Version: 2.1
Name: a5orchestrator
Version: 1.0.7
Summary: This module helps to intigrate Orchestrator with python scripts 
Home-page: https://github.com/akvdkharnath/A5Orchestrator.git
Author: Harnath Atmakuri
Author-email: akvdkharnath@gmail.com
License: MIT
Platform: UNKNOWN
Classifier: Development Status :: 1 - Planning
Classifier: Intended Audience :: Developers
Classifier: Topic :: Software Development :: Libraries
Classifier: License :: OSI Approved :: MIT License
Classifier: Programming Language :: Python :: 2.7
Classifier: Programming Language :: Python :: 3
Requires-Python: >=3.0
Requires-Dist: requests
